config/__init__.py
config/gdrive_config.py
config/notion_config.py
constants/__init__.py
constants/const.py
downloader/__init__.py
downloader/model.py
downloader/service.py
gdrive/__init__.py
gdrive/query_builder.py
gdrive/service.py
markdown/__init__.py
markdown/image_substitution_feeder.py
markdown/service.py
nomark/__init__.py
nomark/config/__init__.py
nomark/config/gdrive_config.py
nomark/config/notion_config.py
nomark/constants/__init__.py
nomark/constants/const.py
nomark/downloader/__init__.py
nomark/downloader/model.py
nomark/downloader/service.py
nomark/gdrive/__init__.py
nomark/gdrive/query_builder.py
nomark/gdrive/service.py
nomark/markdown/__init__.py
nomark/markdown/image_substitution_feeder.py
nomark/markdown/service.py
nomark/notion/__init__.py
nomark/notion/model.py
nomark/notion/repository.py
nomark/notion/service.py
nomark-0.1b0.data/scripts/nomark
notion/__init__.py
notion/model.py
notion/repository.py
notion/service.py
nomark-0.1b0.dist-info/METADATA
nomark-0.1b0.dist-info/WHEEL
nomark-0.1b0.dist-info/top_level.txt
nomark-0.1b0.dist-info/RECORD
