Metadata-Version: 2.1
Name: nomark
Version: 0.1b0
Summary: notion to markdown with image uploader using google drive
Home-page: https://github.com/jen6/nomark
Author: jen6
Author-email: work.jen6@gmail.com
License: MIT
Platform: UNKNOWN
